{
    "board_ed1": {
        "compatible": [ "clue", "m5stack", "microbit", "nodemcu", "pico" ]
    },
    "board_clue": {
        "compatible": [ "microbit", "pico" ]
    },
    "board_cpxbf": {
        "compatible": [ "cpx", "pico" ]
    },
    "board_cpx": {
        "compatible": [ "pico" ]
    },
    "board_calliope": {
        "compatible": [ "microbit", "pico" ]
    },
    "board_microbit": {
        "compatible": [ "pico" ]
    },
    "board_pico": {
        "compatible": [ ]
    },
    "board_nodemcu": {
        "compatible": [ ]
    }
}
